Image_Composer/__init__.py
Image_Composer/_version.py
Image_Composer/image_compose.py
Image_Composer-0.0.19.dist-info/LICENSE
Image_Composer-0.0.19.dist-info/METADATA
Image_Composer-0.0.19.dist-info/WHEEL
Image_Composer-0.0.19.dist-info/entry_points.txt
Image_Composer-0.0.19.dist-info/top_level.txt
Image_Composer-0.0.19.dist-info/RECORD
